cascadict/__init__.py
cascadict/cascadict.py
cascadict/test_cascadict.py
cascadict-0.8.5.dist-info/LICENSE
cascadict-0.8.5.dist-info/METADATA
cascadict-0.8.5.dist-info/WHEEL
cascadict-0.8.5.dist-info/top_level.txt
cascadict-0.8.5.dist-info/RECORD
